README.md
setup.py
lcm_export/__init__.py
lcm_export/lcmlog_export.py
lcm_export/log.py
lcm_export/scan_for_lcmtypes.py
lcm_export.egg-info/PKG-INFO
lcm_export.egg-info/SOURCES.txt
lcm_export.egg-info/dependency_links.txt
lcm_export.egg-info/entry_points.txt
lcm_export.egg-info/top_level.txt