Metadata-Version: 2.1
Name: lcm-export
Version: 1.0.1
Summary: Exports lcm log files to Matlab .mat and Python pickle .pkl files.
Home-page: https://github.com/CaileanWilkinson/lcmlog-export
Author: Cailean Wilkinson
Author-email: cailean.wilkinson@gmail.com
License: LGPL-3.0
Platform: UNKNOWN
Requires-Python: >=3.6
